{
  "nodes": [
    {
      "id": "n0",
      "label": "Corrupción",
      "x": 0,
      "y": 0,
      "size": 18
    },
    {
      "id": "n1",
      "label": "Soborno",
      "x": 1,
      "y": 0,
      "size": 12
    },
    {
      "id": "n2",
      "label": "Extorsión",
      "x": 1,
      "y": 1,
      "size": 6
    },
    {
      "id": "n3",
      "label": "Robo",
      "x": 2,
      "y": 2,
      "size": 15
    },
    {
      "id": "n4",
      "label": "Hurto",
      "x": 3,
      "y": 2,
      "size": 20
    },
    {
      "id": "n5",
      "label": "Cohecho",
      "x": 4,
      "y": 3,
      "size": 8
    },
    {
      "id": "n6",
      "label": "Ilegalidad",
      "x": 5,
      "y": 3,
      "size": 10
    },
    {
      "id": "n7",
      "label": "Enriquecimiento Ilícito",
      "x": 6,
      "y": 4,
      "size": 17
    },
    {
      "id": "n8",
      "label": "Fraude",
      "x": 7,
      "y": 4,
      "size": 12
    },
    {
      "id": "n9",
      "label": "Falsedad",
      "x": 8,
      "y": 5,
      "size": 20
    },
    {
      "id": "n10",
      "label": "Ladrón",
      "x": 9,
      "y": 5,
      "size": 8
    },
    {
      "id": "n11",
      "label": "Torcidos",
      "x": 10,
      "y": 6,
      "size": 15
    },
    {
      "id": "n12",
      "label": "Serrucho",
      "x": 11,
      "y": 6,
      "size": 18
    },
    {
      "id": "n13",
      "label": "Robo",
      "x": 12,
      "y": 7,
      "size": 10
    },
    {
      "id": "n14",
      "label": "Sacar Tajada",
      "x": 13,
      "y": 7,
      "size": 14
    },
    {
      "id": "n15",
      "label": "Robo",
      "x": 14,
      "y": 8,
      "size": 20
    },
    {
      "id": "n16",
      "label": "Ilícito",
      "x": 15,
      "y": 8,
      "size": 8
    },
    {
      "id": "n17",
      "label": "Desfalco",
      "x": 16,
      "y": 9,
      "size": 11
    },
    {
      "id": "n18",
      "label": "Mermelada",
      "x": 17,
      "y": 9,
      "size": 20
    }
  ],
  "edges": [
    {
      "id": "e0",
      "source": "n0",
      "target": "n1"
    },
    {
      "id": "e1",
      "source": "n1",
      "target": "n2"
    },
    {
      "id": "e2",
      "source": "n2",
      "target": "n3"
    },
    {
      "id": "e3",
      "source": "n3",
      "target": "n4"
    },
    {
      "id": "e4",
      "source": "n4",
      "target": "n5"
    },
    {
      "id": "e5",
      "source": "n5",
      "target": "n6"
    },
    {
      "id": "e6",
      "source": "n6",
      "target": "n7"
    },
    {
      "id": "e7",
      "source": "n7",
      "target": "n8"
    },
    {
      "id": "e8",
      "source": "n8",
      "target": "n9"
    },
    {
      "id": "e9",
      "source": "n9",
      "target": "n10"
    },
    {
      "id": "e10",
      "source": "n10",
      "target": "n11"
    },
    {
      "id": "e11",
      "source": "n11",
      "target": "n12"
    },
    {
      "id": "e12",
      "source": "n12",
      "target": "n13"
    },
    {
      "id": "e13",
      "source": "n13",
      "target": "n14"
    },
    {
      "id": "e14",
      "source": "n14",
      "target": "n15"
    },
    {
      "id": "e15",
      "source": "n15",
      "target": "n16"
    },
    {
      "id": "e16",
      "source": "n16",
      "target": "n17"
    },
    {
      "id": "e17",
      "source": "n17",
      "target": "n18"
    }
  ]
}